Metadata-Version: 1.0
Name: pypolymake
Version: 0.1b7
Summary: Python wrapper for polymake
Home-page: UNKNOWN
Author: Vincent Delecroix, Burcin Erocal
Author-email: sage-devel@googlegroups.com
License: GNU General Public License, version 3 or later
Platform: UNKNOWN
